share_gpu/__init__.py
share_gpu/main.py
share_gpu-0.1.0.dist-info/METADATA
share_gpu-0.1.0.dist-info/WHEEL
share_gpu-0.1.0.dist-info/entry_points.txt
share_gpu-0.1.0.dist-info/RECORD
